django_oss_storage/__init__.py
django_oss_storage/backends.py
django_oss_storage/defaults.py
django5.0_oss_storage-1.1.1.dist-info/LICENSE
django5.0_oss_storage-1.1.1.dist-info/METADATA
django5.0_oss_storage-1.1.1.dist-info/WHEEL
django5.0_oss_storage-1.1.1.dist-info/top_level.txt
django5.0_oss_storage-1.1.1.dist-info/RECORD
