Metadata-Version: 2.1
Name: django5.0-oss-storage
Version: 1.1.1
Summary: Django Aliyun OSS (Object Storage Service) storage
Home-page: https://www.aliyun.com/product/oss
Classifier: Development Status :: 5 - Production/Stable
Classifier: Intended Audience :: Developers
Classifier: License :: OSI Approved :: MIT License
Classifier: Operating System :: OS Independent
Classifier: Programming Language :: Python
Classifier: Programming Language :: Python :: 2
Classifier: Programming Language :: Python :: 2.6
Classifier: Programming Language :: Python :: 2.7
Classifier: Programming Language :: Python :: 3
Classifier: Programming Language :: Python :: 3.3
Classifier: Programming Language :: Python :: 3.4
Classifier: Programming Language :: Python :: 3.5
Classifier: Programming Language :: Python :: 3.6
Classifier: Framework :: Django
License-File: LICENSE
Requires-Dist: django >=5.0
Requires-Dist: oss2 >=2.3.3
